UploadgramPyAPI.py
uploadgrampyapi-1.6.1.dist-info/WHEEL
uploadgrampyapi-1.6.1.dist-info/METADATA
uploadgrampyapi-1.6.1.dist-info/RECORD
