Metadata-Version: 2.1
Name: uploadgrampyapi
Version: 1.6.1
Summary: This API can upload, download, remove and rename any files from the service uploadgram.me
Home-page: https://github.com/tankalxat34/UploadgramPyAPI
Author: tankalxat34
Author-email: tankalxat34@gmail.com
Requires-Python: >=3.6,<4.0
Classifier: Programming Language :: Python :: 3
Classifier: Programming Language :: Python :: 3.6
Classifier: Programming Language :: Python :: 3.7
Classifier: Programming Language :: Python :: 3.8
Classifier: Programming Language :: Python :: 3.9
Project-URL: Repository, https://github.com/tankalxat34/UploadgramPyAPI
